README.md
setup.py
llsmartcard/__init__.py
llsmartcard/apdu.py
llsmartcard/card.py
llsmartcard/helper.py
llsmartcard/parser.py
llsmartcard_ph4.egg-info/PKG-INFO
llsmartcard_ph4.egg-info/SOURCES.txt
llsmartcard_ph4.egg-info/dependency_links.txt
llsmartcard_ph4.egg-info/requires.txt
llsmartcard_ph4.egg-info/top_level.txt