Metadata-Version: 2.1
Name: llsmartcard-ph4
Version: 1.1.1
Summary: Module for easily interacting with smartcards.
Home-page: https://github.com/ph4r05/llsmartcard
Author: Chad Spensky
Author-email: chad.spensky@ll.mit.eduasd
Maintainer: Dusan Klinec
Maintainer-email: dusan.klinec@gmail.com
License: MIT
Platform: UNKNOWN
Classifier: Development Status :: 3 - Alpha
Classifier: Intended Audience :: Developers
Classifier: Programming Language :: Python
Classifier: Programming Language :: Python :: 2.6
Classifier: Programming Language :: Python :: 2.7
Classifier: Programming Language :: Python :: 3.5
Classifier: Programming Language :: Python :: 3.6
Classifier: Topic :: Security
Provides-Extra: dev
